faithfulness/BERTScore.py
faithfulness/Baseline.py
faithfulness/Entailment.py
faithfulness/Experimentor.py
faithfulness/NER.py
faithfulness/OpenIE.py
faithfulness/QGQA.py
faithfulness/SRL.py
faithfulness/SRLOLD.py
faithfulness/SentSim.py
faithfulness/__init__.py
faithfulness/interfaces/FaithfulnessInput.py
faithfulness/interfaces/MetricInterface.py
faithfulness/interfaces/SimilarityMetricInterface.py
faithfulness/interfaces/UsesSimilarityMetricInterface.py
faithfulness/interfaces/__init__.py
faithfulness/similarity/ExactMatch.py
faithfulness/similarity/F1.py
faithfulness/similarity/SentCos.py
faithfulness/similarity/__init__.py
faithfulness/types/AlignScoreResult.py
faithfulness/types/GroupedAlignScoreResult.py
faithfulness/types/__init__.py
faithfulness/utils/Datasets.py
faithfulness/utils/__init__.py
faithfulness/utils/correlation.py
faithfulness/utils/representation_utils.py
faithfulness/utils/utils.py
faithfulness/visualization/Visualizer.py
faithfulness/visualization/__init__.py
faithfulness/visualization/visualize_bertscore.py
faithfulness/visualization/visualize_entailment.py
faithfulness/visualization/visualize_ner.py
faithfulness/visualization/visualize_openie.py
faithfulness/visualization/visualize_qgqa.py
faithfulness/visualization/visualize_sentsim.py
faithfulness/visualization/visualize_srl.py
faithfulness-0.0.4.dist-info/LICENSE
faithfulness-0.0.4.dist-info/METADATA
faithfulness-0.0.4.dist-info/WHEEL
faithfulness-0.0.4.dist-info/top_level.txt
faithfulness-0.0.4.dist-info/RECORD
