Metadata-Version: 2.1
Name: faithfulness
Version: 0.0.4
Summary: A library to evaluate faithfulness (factual correctness or consistency) of abstractive summaries.
Home-page: https://github.com/bigabig/faithfulness
Author: Tim Fischer
Author-email: tim.s.fischer96@googlemail.com
License: UNKNOWN
Project-URL: Bug Tracker, https://github.com/bigabig/faithfulness/issues
Platform: UNKNOWN
Classifier: Programming Language :: Python :: 3
Classifier: License :: OSI Approved :: Apache Software License
Classifier: Operating System :: OS Independent
Requires-Python: >=3.6
License-File: LICENSE
Requires-Dist: jsonnet
Requires-Dist: allennlp (==2.1.0)
Requires-Dist: allennlp-models (==2.1.0)
Requires-Dist: transformers
Requires-Dist: stanza
Requires-Dist: sentence-transformers
